{
  "updated": "2026-07-21 14:46 KST",
  "macro": [
    {
      "name": "미국채 30년물",
      "unit": "pct",
      "cur": 5.06,
      "prev": 5.09
    },
    {
      "name": "미국채 10년물",
      "unit": "pct",
      "cur": 4.55,
      "prev": 4.57
    },
    {
      "name": "미국채 2년물",
      "unit": "pct",
      "cur": 4.18,
      "prev": 4.16
    },
    {
      "name": "연준 기준금리",
      "unit": "pct",
      "cur": 3.63,
      "prev": 3.63
    },
    {
      "name": "WTI 유가",
      "unit": "usd",
      "cur": 79.2,
      "prev": 72.45
    },
    {
      "name": "브렌트유",
      "unit": "usd",
      "cur": 81.62,
      "prev": 74.34
    },
    {
      "name": "원/달러",
      "unit": "won",
      "cur": 1489.44,
      "prev": 1478.2
    },
    {
      "name": "VIX",
      "unit": "pt",
      "cur": 18.77,
      "prev": 16.73
    }
  ],
  "dart": [
    {
      "code": "005380",
      "name": "현대차",
      "items": [
        {
          "report": "임원ㆍ주요주주특정증권등소유상황보고서",
          "url": "https://dart.fss.or.kr/dsaf001/main.do?rcpNo=20260720000316",
          "dt": "20260720"
        }
      ]
    },
    {
      "code": "005930",
      "name": "삼성전자",
      "items": [
        {
          "report": "임원ㆍ주요주주특정증권등소유상황보고서",
          "url": "https://dart.fss.or.kr/dsaf001/main.do?rcpNo=20260721000585",
          "dt": "20260721"
        },
        {
          "report": "임원ㆍ주요주주특정증권등소유상황보고서",
          "url": "https://dart.fss.or.kr/dsaf001/main.do?rcpNo=20260721000583",
          "dt": "20260721"
        },
        {
          "report": "임원ㆍ주요주주특정증권등소유상황보고서",
          "url": "https://dart.fss.or.kr/dsaf001/main.do?rcpNo=20260721000581",
          "dt": "20260721"
        },
        {
          "report": "임원ㆍ주요주주특정증권등소유상황보고서",
          "url": "https://dart.fss.or.kr/dsaf001/main.do?rcpNo=20260721000580",
          "dt": "20260721"
        },
        {
          "report": "임원ㆍ주요주주특정증권등소유상황보고서",
          "url": "https://dart.fss.or.kr/dsaf001/main.do?rcpNo=20260721000578",
          "dt": "20260721"
        },
        {
          "report": "임원ㆍ주요주주특정증권등소유상황보고서",
          "url": "https://dart.fss.or.kr/dsaf001/main.do?rcpNo=20260721000576",
          "dt": "20260721"
        },
        {
          "report": "임원ㆍ주요주주특정증권등소유상황보고서",
          "url": "https://dart.fss.or.kr/dsaf001/main.do?rcpNo=20260721000575",
          "dt": "20260721"
        },
        {
          "report": "임원ㆍ주요주주특정증권등소유상황보고서",
          "url": "https://dart.fss.or.kr/dsaf001/main.do?rcpNo=20260721000573",
          "dt": "20260721"
        },
        {
          "report": "임원ㆍ주요주주특정증권등소유상황보고서",
          "url": "https://dart.fss.or.kr/dsaf001/main.do?rcpNo=20260721000572",
          "dt": "20260721"
        },
        {
          "report": "임원ㆍ주요주주특정증권등소유상황보고서",
          "url": "https://dart.fss.or.kr/dsaf001/main.do?rcpNo=20260721000571",
          "dt": "20260721"
        },
        {
          "report": "임원ㆍ주요주주특정증권등소유상황보고서",
          "url": "https://dart.fss.or.kr/dsaf001/main.do?rcpNo=20260721000569",
          "dt": "20260721"
        },
        {
          "report": "임원ㆍ주요주주특정증권등소유상황보고서",
          "url": "https://dart.fss.or.kr/dsaf001/main.do?rcpNo=20260721000568",
          "dt": "20260721"
        },
        {
          "report": "임원ㆍ주요주주특정증권등소유상황보고서",
          "url": "https://dart.fss.or.kr/dsaf001/main.do?rcpNo=20260721000567",
          "dt": "20260721"
        },
        {
          "report": "임원ㆍ주요주주특정증권등소유상황보고서",
          "url": "https://dart.fss.or.kr/dsaf001/main.do?rcpNo=20260721000565",
          "dt": "20260721"
        },
        {
          "report": "임원ㆍ주요주주특정증권등소유상황보고서",
          "url": "https://dart.fss.or.kr/dsaf001/main.do?rcpNo=20260721000564",
          "dt": "20260721"
        },
        {
          "report": "임원ㆍ주요주주특정증권등소유상황보고서",
          "url": "https://dart.fss.or.kr/dsaf001/main.do?rcpNo=20260721000563",
          "dt": "20260721"
        },
        {
          "report": "임원ㆍ주요주주특정증권등소유상황보고서",
          "url": "https://dart.fss.or.kr/dsaf001/main.do?rcpNo=20260721000560",
          "dt": "20260721"
        },
        {
          "report": "임원ㆍ주요주주특정증권등소유상황보고서",
          "url": "https://dart.fss.or.kr/dsaf001/main.do?rcpNo=20260721000559",
          "dt": "20260721"
        },
        {
          "report": "임원ㆍ주요주주특정증권등소유상황보고서",
          "url": "https://dart.fss.or.kr/dsaf001/main.do?rcpNo=20260721000558",
          "dt": "20260721"
        },
        {
          "report": "임원ㆍ주요주주특정증권등소유상황보고서",
          "url": "https://dart.fss.or.kr/dsaf001/main.do?rcpNo=20260721000557",
          "dt": "20260721"
        },
        {
          "report": "임원ㆍ주요주주특정증권등소유상황보고서",
          "url": "https://dart.fss.or.kr/dsaf001/main.do?rcpNo=20260721000556",
          "dt": "20260721"
        },
        {
          "report": "임원ㆍ주요주주특정증권등소유상황보고서",
          "url": "https://dart.fss.or.kr/dsaf001/main.do?rcpNo=20260721000554",
          "dt": "20260721"
        },
        {
          "report": "임원ㆍ주요주주특정증권등소유상황보고서",
          "url": "https://dart.fss.or.kr/dsaf001/main.do?rcpNo=20260721000553",
          "dt": "20260721"
        },
        {
          "report": "임원ㆍ주요주주특정증권등소유상황보고서",
          "url": "https://dart.fss.or.kr/dsaf001/main.do?rcpNo=20260721000551",
          "dt": "20260721"
        },
        {
          "report": "임원ㆍ주요주주특정증권등소유상황보고서",
          "url": "https://dart.fss.or.kr/dsaf001/main.do?rcpNo=20260721000549",
          "dt": "20260721"
        },
        {
          "report": "임원ㆍ주요주주특정증권등소유상황보고서",
          "url": "https://dart.fss.or.kr/dsaf001/main.do?rcpNo=20260721000548",
          "dt": "20260721"
        },
        {
          "report": "임원ㆍ주요주주특정증권등소유상황보고서",
          "url": "https://dart.fss.or.kr/dsaf001/main.do?rcpNo=20260721000547",
          "dt": "20260721"
        },
        {
          "report": "임원ㆍ주요주주특정증권등소유상황보고서",
          "url": "https://dart.fss.or.kr/dsaf001/main.do?rcpNo=20260721000546",
          "dt": "20260721"
        },
        {
          "report": "임원ㆍ주요주주특정증권등소유상황보고서",
          "url": "https://dart.fss.or.kr/dsaf001/main.do?rcpNo=20260721000544",
          "dt": "20260721"
        },
        {
          "report": "임원ㆍ주요주주특정증권등소유상황보고서",
          "url": "https://dart.fss.or.kr/dsaf001/main.do?rcpNo=20260721000543",
          "dt": "20260721"
        },
        {
          "report": "임원ㆍ주요주주특정증권등소유상황보고서",
          "url": "https://dart.fss.or.kr/dsaf001/main.do?rcpNo=20260721000542",
          "dt": "20260721"
        },
        {
          "report": "임원ㆍ주요주주특정증권등소유상황보고서",
          "url": "https://dart.fss.or.kr/dsaf001/main.do?rcpNo=20260721000541",
          "dt": "20260721"
        },
        {
          "report": "임원ㆍ주요주주특정증권등소유상황보고서",
          "url": "https://dart.fss.or.kr/dsaf001/main.do?rcpNo=20260721000540",
          "dt": "20260721"
        },
        {
          "report": "임원ㆍ주요주주특정증권등소유상황보고서",
          "url": "https://dart.fss.or.kr/dsaf001/main.do?rcpNo=20260721000538",
          "dt": "20260721"
        },
        {
          "report": "임원ㆍ주요주주특정증권등소유상황보고서",
          "url": "https://dart.fss.or.kr/dsaf001/main.do?rcpNo=20260721000536",
          "dt": "20260721"
        },
        {
          "report": "임원ㆍ주요주주특정증권등소유상황보고서",
          "url": "https://dart.fss.or.kr/dsaf001/main.do?rcpNo=20260721000535",
          "dt": "20260721"
        },
        {
          "report": "임원ㆍ주요주주특정증권등소유상황보고서",
          "url": "https://dart.fss.or.kr/dsaf001/main.do?rcpNo=20260721000533",
          "dt": "20260721"
        },
        {
          "report": "임원ㆍ주요주주특정증권등소유상황보고서",
          "url": "https://dart.fss.or.kr/dsaf001/main.do?rcpNo=20260721000531",
          "dt": "20260721"
        },
        {
          "report": "임원ㆍ주요주주특정증권등소유상황보고서",
          "url": "https://dart.fss.or.kr/dsaf001/main.do?rcpNo=20260721000530",
          "dt": "20260721"
        },
        {
          "report": "임원ㆍ주요주주특정증권등소유상황보고서",
          "url": "https://dart.fss.or.kr/dsaf001/main.do?rcpNo=20260721000529",
          "dt": "20260721"
        },
        {
          "report": "임원ㆍ주요주주특정증권등소유상황보고서",
          "url": "https://dart.fss.or.kr/dsaf001/main.do?rcpNo=20260721000526",
          "dt": "20260721"
        },
        {
          "report": "임원ㆍ주요주주특정증권등소유상황보고서",
          "url": "https://dart.fss.or.kr/dsaf001/main.do?rcpNo=20260721000524",
          "dt": "20260721"
        },
        {
          "report": "임원ㆍ주요주주특정증권등소유상황보고서",
          "url": "https://dart.fss.or.kr/dsaf001/main.do?rcpNo=20260721000523",
          "dt": "20260721"
        },
        {
          "report": "임원ㆍ주요주주특정증권등소유상황보고서",
          "url": "https://dart.fss.or.kr/dsaf001/main.do?rcpNo=20260721000522",
          "dt": "20260721"
        },
        {
          "report": "임원ㆍ주요주주특정증권등소유상황보고서",
          "url": "https://dart.fss.or.kr/dsaf001/main.do?rcpNo=20260721000519",
          "dt": "20260721"
        },
        {
          "report": "임원ㆍ주요주주특정증권등소유상황보고서",
          "url": "https://dart.fss.or.kr/dsaf001/main.do?rcpNo=20260721000518",
          "dt": "20260721"
        },
        {
          "report": "임원ㆍ주요주주특정증권등소유상황보고서",
          "url": "https://dart.fss.or.kr/dsaf001/main.do?rcpNo=20260721000517",
          "dt": "20260721"
        },
        {
          "report": "임원ㆍ주요주주특정증권등소유상황보고서",
          "url": "https://dart.fss.or.kr/dsaf001/main.do?rcpNo=20260721000516",
          "dt": "20260721"
        },
        {
          "report": "임원ㆍ주요주주특정증권등소유상황보고서",
          "url": "https://dart.fss.or.kr/dsaf001/main.do?rcpNo=20260721000515",
          "dt": "20260721"
        },
        {
          "report": "임원ㆍ주요주주특정증권등소유상황보고서",
          "url": "https://dart.fss.or.kr/dsaf001/main.do?rcpNo=20260721000513",
          "dt": "20260721"
        },
        {
          "report": "임원ㆍ주요주주특정증권등소유상황보고서",
          "url": "https://dart.fss.or.kr/dsaf001/main.do?rcpNo=20260721000509",
          "dt": "20260721"
        },
        {
          "report": "임원ㆍ주요주주특정증권등소유상황보고서",
          "url": "https://dart.fss.or.kr/dsaf001/main.do?rcpNo=20260721000508",
          "dt": "20260721"
        },
        {
          "report": "임원ㆍ주요주주특정증권등소유상황보고서",
          "url": "https://dart.fss.or.kr/dsaf001/main.do?rcpNo=20260721000507",
          "dt": "20260721"
        },
        {
          "report": "임원ㆍ주요주주특정증권등소유상황보고서",
          "url": "https://dart.fss.or.kr/dsaf001/main.do?rcpNo=20260721000506",
          "dt": "20260721"
        },
        {
          "report": "임원ㆍ주요주주특정증권등소유상황보고서",
          "url": "https://dart.fss.or.kr/dsaf001/main.do?rcpNo=20260721000504",
          "dt": "20260721"
        },
        {
          "report": "임원ㆍ주요주주특정증권등소유상황보고서",
          "url": "https://dart.fss.or.kr/dsaf001/main.do?rcpNo=20260721000503",
          "dt": "20260721"
        },
        {
          "report": "임원ㆍ주요주주특정증권등소유상황보고서",
          "url": "https://dart.fss.or.kr/dsaf001/main.do?rcpNo=20260721000502",
          "dt": "20260721"
        },
        {
          "report": "임원ㆍ주요주주특정증권등소유상황보고서",
          "url": "https://dart.fss.or.kr/dsaf001/main.do?rcpNo=20260721000500",
          "dt": "20260721"
        },
        {
          "report": "임원ㆍ주요주주특정증권등소유상황보고서",
          "url": "https://dart.fss.or.kr/dsaf001/main.do?rcpNo=20260721000497",
          "dt": "20260721"
        },
        {
          "report": "임원ㆍ주요주주특정증권등소유상황보고서",
          "url": "https://dart.fss.or.kr/dsaf001/main.do?rcpNo=20260721000494",
          "dt": "20260721"
        },
        {
          "report": "임원ㆍ주요주주특정증권등소유상황보고서",
          "url": "https://dart.fss.or.kr/dsaf001/main.do?rcpNo=20260721000491",
          "dt": "20260721"
        },
        {
          "report": "임원ㆍ주요주주특정증권등소유상황보고서",
          "url": "https://dart.fss.or.kr/dsaf001/main.do?rcpNo=20260721000490",
          "dt": "20260721"
        },
        {
          "report": "임원ㆍ주요주주특정증권등소유상황보고서",
          "url": "https://dart.fss.or.kr/dsaf001/main.do?rcpNo=20260721000489",
          "dt": "20260721"
        },
        {
          "report": "임원ㆍ주요주주특정증권등소유상황보고서",
          "url": "https://dart.fss.or.kr/dsaf001/main.do?rcpNo=20260721000486",
          "dt": "20260721"
        },
        {
          "report": "임원ㆍ주요주주특정증권등소유상황보고서",
          "url": "https://dart.fss.or.kr/dsaf001/main.do?rcpNo=20260721000485",
          "dt": "20260721"
        },
        {
          "report": "임원ㆍ주요주주특정증권등소유상황보고서",
          "url": "https://dart.fss.or.kr/dsaf001/main.do?rcpNo=20260721000483",
          "dt": "20260721"
        },
        {
          "report": "임원ㆍ주요주주특정증권등소유상황보고서",
          "url": "https://dart.fss.or.kr/dsaf001/main.do?rcpNo=20260721000482",
          "dt": "20260721"
        },
        {
          "report": "임원ㆍ주요주주특정증권등소유상황보고서",
          "url": "https://dart.fss.or.kr/dsaf001/main.do?rcpNo=20260721000481",
          "dt": "20260721"
        },
        {
          "report": "임원ㆍ주요주주특정증권등소유상황보고서",
          "url": "https://dart.fss.or.kr/dsaf001/main.do?rcpNo=20260721000480",
          "dt": "20260721"
        },
        {
          "report": "임원ㆍ주요주주특정증권등소유상황보고서",
          "url": "https://dart.fss.or.kr/dsaf001/main.do?rcpNo=20260721000478",
          "dt": "20260721"
        },
        {
          "report": "임원ㆍ주요주주특정증권등소유상황보고서",
          "url": "https://dart.fss.or.kr/dsaf001/main.do?rcpNo=20260721000477",
          "dt": "20260721"
        },
        {
          "report": "임원ㆍ주요주주특정증권등소유상황보고서",
          "url": "https://dart.fss.or.kr/dsaf001/main.do?rcpNo=20260721000474",
          "dt": "20260721"
        },
        {
          "report": "임원ㆍ주요주주특정증권등소유상황보고서",
          "url": "https://dart.fss.or.kr/dsaf001/main.do?rcpNo=20260721000471",
          "dt": "20260721"
        },
        {
          "report": "임원ㆍ주요주주특정증권등소유상황보고서",
          "url": "https://dart.fss.or.kr/dsaf001/main.do?rcpNo=20260721000469",
          "dt": "20260721"
        },
        {
          "report": "임원ㆍ주요주주특정증권등소유상황보고서",
          "url": "https://dart.fss.or.kr/dsaf001/main.do?rcpNo=20260721000467",
          "dt": "20260721"
        },
        {
          "report": "임원ㆍ주요주주특정증권등소유상황보고서",
          "url": "https://dart.fss.or.kr/dsaf001/main.do?rcpNo=20260721000465",
          "dt": "20260721"
        },
        {
          "report": "임원ㆍ주요주주특정증권등소유상황보고서",
          "url": "https://dart.fss.or.kr/dsaf001/main.do?rcpNo=20260721000463",
          "dt": "20260721"
        },
        {
          "report": "임원ㆍ주요주주특정증권등소유상황보고서",
          "url": "https://dart.fss.or.kr/dsaf001/main.do?rcpNo=20260721000462",
          "dt": "20260721"
        },
        {
          "report": "임원ㆍ주요주주특정증권등소유상황보고서",
          "url": "https://dart.fss.or.kr/dsaf001/main.do?rcpNo=20260721000460",
          "dt": "20260721"
        },
        {
          "report": "임원ㆍ주요주주특정증권등소유상황보고서",
          "url": "https://dart.fss.or.kr/dsaf001/main.do?rcpNo=20260721000459",
          "dt": "20260721"
        },
        {
          "report": "임원ㆍ주요주주특정증권등소유상황보고서",
          "url": "https://dart.fss.or.kr/dsaf001/main.do?rcpNo=20260721000458",
          "dt": "20260721"
        },
        {
          "report": "임원ㆍ주요주주특정증권등소유상황보고서",
          "url": "https://dart.fss.or.kr/dsaf001/main.do?rcpNo=20260721000457",
          "dt": "20260721"
        },
        {
          "report": "임원ㆍ주요주주특정증권등소유상황보고서",
          "url": "https://dart.fss.or.kr/dsaf001/main.do?rcpNo=20260721000455",
          "dt": "20260721"
        },
        {
          "report": "임원ㆍ주요주주특정증권등소유상황보고서",
          "url": "https://dart.fss.or.kr/dsaf001/main.do?rcpNo=20260721000454",
          "dt": "20260721"
        },
        {
          "report": "임원ㆍ주요주주특정증권등소유상황보고서",
          "url": "https://dart.fss.or.kr/dsaf001/main.do?rcpNo=20260721000453",
          "dt": "20260721"
        },
        {
          "report": "임원ㆍ주요주주특정증권등소유상황보고서",
          "url": "https://dart.fss.or.kr/dsaf001/main.do?rcpNo=20260721000451",
          "dt": "20260721"
        },
        {
          "report": "임원ㆍ주요주주특정증권등소유상황보고서",
          "url": "https://dart.fss.or.kr/dsaf001/main.do?rcpNo=20260721000448",
          "dt": "20260721"
        },
        {
          "report": "임원ㆍ주요주주특정증권등소유상황보고서",
          "url": "https://dart.fss.or.kr/dsaf001/main.do?rcpNo=20260721000447",
          "dt": "20260721"
        },
        {
          "report": "임원ㆍ주요주주특정증권등소유상황보고서",
          "url": "https://dart.fss.or.kr/dsaf001/main.do?rcpNo=20260721000446",
          "dt": "20260721"
        },
        {
          "report": "임원ㆍ주요주주특정증권등소유상황보고서",
          "url": "https://dart.fss.or.kr/dsaf001/main.do?rcpNo=20260721000443",
          "dt": "20260721"
        },
        {
          "report": "임원ㆍ주요주주특정증권등소유상황보고서",
          "url": "https://dart.fss.or.kr/dsaf001/main.do?rcpNo=20260721000442",
          "dt": "20260721"
        },
        {
          "report": "임원ㆍ주요주주특정증권등소유상황보고서",
          "url": "https://dart.fss.or.kr/dsaf001/main.do?rcpNo=20260721000441",
          "dt": "20260721"
        },
        {
          "report": "임원ㆍ주요주주특정증권등소유상황보고서",
          "url": "https://dart.fss.or.kr/dsaf001/main.do?rcpNo=20260721000440",
          "dt": "20260721"
        },
        {
          "report": "임원ㆍ주요주주특정증권등소유상황보고서",
          "url": "https://dart.fss.or.kr/dsaf001/main.do?rcpNo=20260721000436",
          "dt": "20260721"
        },
        {
          "report": "임원ㆍ주요주주특정증권등소유상황보고서",
          "url": "https://dart.fss.or.kr/dsaf001/main.do?rcpNo=20260721000435",
          "dt": "20260721"
        },
        {
          "report": "임원ㆍ주요주주특정증권등소유상황보고서",
          "url": "https://dart.fss.or.kr/dsaf001/main.do?rcpNo=20260721000433",
          "dt": "20260721"
        },
        {
          "report": "임원ㆍ주요주주특정증권등소유상황보고서",
          "url": "https://dart.fss.or.kr/dsaf001/main.do?rcpNo=20260721000432",
          "dt": "20260721"
        },
        {
          "report": "임원ㆍ주요주주특정증권등소유상황보고서",
          "url": "https://dart.fss.or.kr/dsaf001/main.do?rcpNo=20260721000430",
          "dt": "20260721"
        },
        {
          "report": "임원ㆍ주요주주특정증권등소유상황보고서",
          "url": "https://dart.fss.or.kr/dsaf001/main.do?rcpNo=20260721000426",
          "dt": "20260721"
        },
        {
          "report": "임원ㆍ주요주주특정증권등소유상황보고서",
          "url": "https://dart.fss.or.kr/dsaf001/main.do?rcpNo=20260721000424",
          "dt": "20260721"
        },
        {
          "report": "임원ㆍ주요주주특정증권등소유상황보고서",
          "url": "https://dart.fss.or.kr/dsaf001/main.do?rcpNo=20260721000423",
          "dt": "20260721"
        },
        {
          "report": "임원ㆍ주요주주특정증권등소유상황보고서",
          "url": "https://dart.fss.or.kr/dsaf001/main.do?rcpNo=20260721000420",
          "dt": "20260721"
        },
        {
          "report": "임원ㆍ주요주주특정증권등소유상황보고서",
          "url": "https://dart.fss.or.kr/dsaf001/main.do?rcpNo=20260721000419",
          "dt": "20260721"
        },
        {
          "report": "임원ㆍ주요주주특정증권등소유상황보고서",
          "url": "https://dart.fss.or.kr/dsaf001/main.do?rcpNo=20260721000416",
          "dt": "20260721"
        },
        {
          "report": "임원ㆍ주요주주특정증권등소유상황보고서",
          "url": "https://dart.fss.or.kr/dsaf001/main.do?rcpNo=20260721000415",
          "dt": "20260721"
        },
        {
          "report": "임원ㆍ주요주주특정증권등소유상황보고서",
          "url": "https://dart.fss.or.kr/dsaf001/main.do?rcpNo=20260721000414",
          "dt": "20260721"
        },
        {
          "report": "임원ㆍ주요주주특정증권등소유상황보고서",
          "url": "https://dart.fss.or.kr/dsaf001/main.do?rcpNo=20260721000412",
          "dt": "20260721"
        },
        {
          "report": "임원ㆍ주요주주특정증권등소유상황보고서",
          "url": "https://dart.fss.or.kr/dsaf001/main.do?rcpNo=20260721000411",
          "dt": "20260721"
        },
        {
          "report": "임원ㆍ주요주주특정증권등소유상황보고서",
          "url": "https://dart.fss.or.kr/dsaf001/main.do?rcpNo=20260721000410",
          "dt": "20260721"
        },
        {
          "report": "임원ㆍ주요주주특정증권등소유상황보고서",
          "url": "https://dart.fss.or.kr/dsaf001/main.do?rcpNo=20260721000409",
          "dt": "20260721"
        },
        {
          "report": "임원ㆍ주요주주특정증권등소유상황보고서",
          "url": "https://dart.fss.or.kr/dsaf001/main.do?rcpNo=20260721000408",
          "dt": "20260721"
        },
        {
          "report": "임원ㆍ주요주주특정증권등소유상황보고서",
          "url": "https://dart.fss.or.kr/dsaf001/main.do?rcpNo=20260721000406",
          "dt": "20260721"
        },
        {
          "report": "임원ㆍ주요주주특정증권등소유상황보고서",
          "url": "https://dart.fss.or.kr/dsaf001/main.do?rcpNo=20260721000404",
          "dt": "20260721"
        },
        {
          "report": "임원ㆍ주요주주특정증권등소유상황보고서",
          "url": "https://dart.fss.or.kr/dsaf001/main.do?rcpNo=20260721000403",
          "dt": "20260721"
        },
        {
          "report": "임원ㆍ주요주주특정증권등소유상황보고서",
          "url": "https://dart.fss.or.kr/dsaf001/main.do?rcpNo=20260721000402",
          "dt": "20260721"
        },
        {
          "report": "임원ㆍ주요주주특정증권등소유상황보고서",
          "url": "https://dart.fss.or.kr/dsaf001/main.do?rcpNo=20260721000401",
          "dt": "20260721"
        },
        {
          "report": "임원ㆍ주요주주특정증권등소유상황보고서",
          "url": "https://dart.fss.or.kr/dsaf001/main.do?rcpNo=20260721000399",
          "dt": "20260721"
        },
        {
          "report": "임원ㆍ주요주주특정증권등소유상황보고서",
          "url": "https://dart.fss.or.kr/dsaf001/main.do?rcpNo=20260721000397",
          "dt": "20260721"
        },
        {
          "report": "임원ㆍ주요주주특정증권등소유상황보고서",
          "url": "https://dart.fss.or.kr/dsaf001/main.do?rcpNo=20260721000396",
          "dt": "20260721"
        },
        {
          "report": "임원ㆍ주요주주특정증권등소유상황보고서",
          "url": "https://dart.fss.or.kr/dsaf001/main.do?rcpNo=20260721000394",
          "dt": "20260721"
        },
        {
          "report": "임원ㆍ주요주주특정증권등소유상황보고서",
          "url": "https://dart.fss.or.kr/dsaf001/main.do?rcpNo=20260721000393",
          "dt": "20260721"
        },
        {
          "report": "임원ㆍ주요주주특정증권등소유상황보고서",
          "url": "https://dart.fss.or.kr/dsaf001/main.do?rcpNo=20260721000392",
          "dt": "20260721"
        },
        {
          "report": "임원ㆍ주요주주특정증권등소유상황보고서",
          "url": "https://dart.fss.or.kr/dsaf001/main.do?rcpNo=20260721000391",
          "dt": "20260721"
        },
        {
          "report": "임원ㆍ주요주주특정증권등소유상황보고서",
          "url": "https://dart.fss.or.kr/dsaf001/main.do?rcpNo=20260721000387",
          "dt": "20260721"
        },
        {
          "report": "임원ㆍ주요주주특정증권등소유상황보고서",
          "url": "https://dart.fss.or.kr/dsaf001/main.do?rcpNo=20260721000384",
          "dt": "20260721"
        },
        {
          "report": "임원ㆍ주요주주특정증권등소유상황보고서",
          "url": "https://dart.fss.or.kr/dsaf001/main.do?rcpNo=20260721000382",
          "dt": "20260721"
        },
        {
          "report": "임원ㆍ주요주주특정증권등소유상황보고서",
          "url": "https://dart.fss.or.kr/dsaf001/main.do?rcpNo=20260721000381",
          "dt": "20260721"
        },
        {
          "report": "임원ㆍ주요주주특정증권등소유상황보고서",
          "url": "https://dart.fss.or.kr/dsaf001/main.do?rcpNo=20260721000380",
          "dt": "20260721"
        },
        {
          "report": "임원ㆍ주요주주특정증권등소유상황보고서",
          "url": "https://dart.fss.or.kr/dsaf001/main.do?rcpNo=20260721000377",
          "dt": "20260721"
        },
        {
          "report": "임원ㆍ주요주주특정증권등소유상황보고서",
          "url": "https://dart.fss.or.kr/dsaf001/main.do?rcpNo=20260721000376",
          "dt": "20260721"
        },
        {
          "report": "임원ㆍ주요주주특정증권등소유상황보고서",
          "url": "https://dart.fss.or.kr/dsaf001/main.do?rcpNo=20260721000375",
          "dt": "20260721"
        },
        {
          "report": "임원ㆍ주요주주특정증권등소유상황보고서",
          "url": "https://dart.fss.or.kr/dsaf001/main.do?rcpNo=20260721000374",
          "dt": "20260721"
        },
        {
          "report": "임원ㆍ주요주주특정증권등소유상황보고서",
          "url": "https://dart.fss.or.kr/dsaf001/main.do?rcpNo=20260721000371",
          "dt": "20260721"
        },
        {
          "report": "임원ㆍ주요주주특정증권등소유상황보고서",
          "url": "https://dart.fss.or.kr/dsaf001/main.do?rcpNo=20260721000370",
          "dt": "20260721"
        },
        {
          "report": "임원ㆍ주요주주특정증권등소유상황보고서",
          "url": "https://dart.fss.or.kr/dsaf001/main.do?rcpNo=20260721000369",
          "dt": "20260721"
        },
        {
          "report": "임원ㆍ주요주주특정증권등소유상황보고서",
          "url": "https://dart.fss.or.kr/dsaf001/main.do?rcpNo=20260721000368",
          "dt": "20260721"
        },
        {
          "report": "임원ㆍ주요주주특정증권등소유상황보고서",
          "url": "https://dart.fss.or.kr/dsaf001/main.do?rcpNo=20260721000366",
          "dt": "20260721"
        },
        {
          "report": "임원ㆍ주요주주특정증권등소유상황보고서",
          "url": "https://dart.fss.or.kr/dsaf001/main.do?rcpNo=20260721000365",
          "dt": "20260721"
        },
        {
          "report": "임원ㆍ주요주주특정증권등소유상황보고서",
          "url": "https://dart.fss.or.kr/dsaf001/main.do?rcpNo=20260721000364",
          "dt": "20260721"
        },
        {
          "report": "임원ㆍ주요주주특정증권등소유상황보고서",
          "url": "https://dart.fss.or.kr/dsaf001/main.do?rcpNo=20260721000363",
          "dt": "20260721"
        },
        {
          "report": "임원ㆍ주요주주특정증권등소유상황보고서",
          "url": "https://dart.fss.or.kr/dsaf001/main.do?rcpNo=20260721000362",
          "dt": "20260721"
        },
        {
          "report": "임원ㆍ주요주주특정증권등소유상황보고서",
          "url": "https://dart.fss.or.kr/dsaf001/main.do?rcpNo=20260721000361",
          "dt": "20260721"
        },
        {
          "report": "임원ㆍ주요주주특정증권등소유상황보고서",
          "url": "https://dart.fss.or.kr/dsaf001/main.do?rcpNo=20260721000360",
          "dt": "20260721"
        },
        {
          "report": "임원ㆍ주요주주특정증권등소유상황보고서",
          "url": "https://dart.fss.or.kr/dsaf001/main.do?rcpNo=20260721000359",
          "dt": "20260721"
        },
        {
          "report": "임원ㆍ주요주주특정증권등소유상황보고서",
          "url": "https://dart.fss.or.kr/dsaf001/main.do?rcpNo=20260721000357",
          "dt": "20260721"
        },
        {
          "report": "임원ㆍ주요주주특정증권등소유상황보고서",
          "url": "https://dart.fss.or.kr/dsaf001/main.do?rcpNo=20260721000356",
          "dt": "20260721"
        },
        {
          "report": "임원ㆍ주요주주특정증권등소유상황보고서",
          "url": "https://dart.fss.or.kr/dsaf001/main.do?rcpNo=20260721000353",
          "dt": "20260721"
        },
        {
          "report": "임원ㆍ주요주주특정증권등소유상황보고서",
          "url": "https://dart.fss.or.kr/dsaf001/main.do?rcpNo=20260721000352",
          "dt": "20260721"
        },
        {
          "report": "임원ㆍ주요주주특정증권등소유상황보고서",
          "url": "https://dart.fss.or.kr/dsaf001/main.do?rcpNo=20260721000351",
          "dt": "20260721"
        },
        {
          "report": "임원ㆍ주요주주특정증권등소유상황보고서",
          "url": "https://dart.fss.or.kr/dsaf001/main.do?rcpNo=20260721000349",
          "dt": "20260721"
        },
        {
          "report": "임원ㆍ주요주주특정증권등소유상황보고서",
          "url": "https://dart.fss.or.kr/dsaf001/main.do?rcpNo=20260721000346",
          "dt": "20260721"
        },
        {
          "report": "임원ㆍ주요주주특정증권등소유상황보고서",
          "url": "https://dart.fss.or.kr/dsaf001/main.do?rcpNo=20260721000345",
          "dt": "20260721"
        },
        {
          "report": "임원ㆍ주요주주특정증권등소유상황보고서",
          "url": "https://dart.fss.or.kr/dsaf001/main.do?rcpNo=20260721000342",
          "dt": "20260721"
        },
        {
          "report": "임원ㆍ주요주주특정증권등소유상황보고서",
          "url": "https://dart.fss.or.kr/dsaf001/main.do?rcpNo=20260721000341",
          "dt": "20260721"
        },
        {
          "report": "임원ㆍ주요주주특정증권등소유상황보고서",
          "url": "https://dart.fss.or.kr/dsaf001/main.do?rcpNo=20260721000340",
          "dt": "20260721"
        },
        {
          "report": "임원ㆍ주요주주특정증권등소유상황보고서",
          "url": "https://dart.fss.or.kr/dsaf001/main.do?rcpNo=20260721000339",
          "dt": "20260721"
        },
        {
          "report": "임원ㆍ주요주주특정증권등소유상황보고서",
          "url": "https://dart.fss.or.kr/dsaf001/main.do?rcpNo=20260721000338",
          "dt": "20260721"
        },
        {
          "report": "임원ㆍ주요주주특정증권등소유상황보고서",
          "url": "https://dart.fss.or.kr/dsaf001/main.do?rcpNo=20260721000335",
          "dt": "20260721"
        },
        {
          "report": "임원ㆍ주요주주특정증권등소유상황보고서",
          "url": "https://dart.fss.or.kr/dsaf001/main.do?rcpNo=20260721000333",
          "dt": "20260721"
        },
        {
          "report": "임원ㆍ주요주주특정증권등소유상황보고서",
          "url": "https://dart.fss.or.kr/dsaf001/main.do?rcpNo=20260721000332",
          "dt": "20260721"
        },
        {
          "report": "임원ㆍ주요주주특정증권등소유상황보고서",
          "url": "https://dart.fss.or.kr/dsaf001/main.do?rcpNo=20260721000328",
          "dt": "20260721"
        },
        {
          "report": "임원ㆍ주요주주특정증권등소유상황보고서",
          "url": "https://dart.fss.or.kr/dsaf001/main.do?rcpNo=20260721000327",
          "dt": "20260721"
        },
        {
          "report": "임원ㆍ주요주주특정증권등소유상황보고서",
          "url": "https://dart.fss.or.kr/dsaf001/main.do?rcpNo=20260721000326",
          "dt": "20260721"
        },
        {
          "report": "임원ㆍ주요주주특정증권등소유상황보고서",
          "url": "https://dart.fss.or.kr/dsaf001/main.do?rcpNo=20260721000324",
          "dt": "20260721"
        },
        {
          "report": "임원ㆍ주요주주특정증권등소유상황보고서",
          "url": "https://dart.fss.or.kr/dsaf001/main.do?rcpNo=20260721000323",
          "dt": "20260721"
        },
        {
          "report": "임원ㆍ주요주주특정증권등소유상황보고서",
          "url": "https://dart.fss.or.kr/dsaf001/main.do?rcpNo=20260721000318",
          "dt": "20260721"
        },
        {
          "report": "임원ㆍ주요주주특정증권등소유상황보고서",
          "url": "https://dart.fss.or.kr/dsaf001/main.do?rcpNo=20260721000317",
          "dt": "20260721"
        },
        {
          "report": "임원ㆍ주요주주특정증권등소유상황보고서",
          "url": "https://dart.fss.or.kr/dsaf001/main.do?rcpNo=20260721000316",
          "dt": "20260721"
        },
        {
          "report": "임원ㆍ주요주주특정증권등소유상황보고서",
          "url": "https://dart.fss.or.kr/dsaf001/main.do?rcpNo=20260721000314",
          "dt": "20260721"
        },
        {
          "report": "임원ㆍ주요주주특정증권등소유상황보고서",
          "url": "https://dart.fss.or.kr/dsaf001/main.do?rcpNo=20260721000313",
          "dt": "20260721"
        },
        {
          "report": "임원ㆍ주요주주특정증권등소유상황보고서",
          "url": "https://dart.fss.or.kr/dsaf001/main.do?rcpNo=20260721000310",
          "dt": "20260721"
        },
        {
          "report": "임원ㆍ주요주주특정증권등소유상황보고서",
          "url": "https://dart.fss.or.kr/dsaf001/main.do?rcpNo=20260721000309",
          "dt": "20260721"
        },
        {
          "report": "임원ㆍ주요주주특정증권등소유상황보고서",
          "url": "https://dart.fss.or.kr/dsaf001/main.do?rcpNo=20260721000306",
          "dt": "20260721"
        },
        {
          "report": "임원ㆍ주요주주특정증권등소유상황보고서",
          "url": "https://dart.fss.or.kr/dsaf001/main.do?rcpNo=20260721000305",
          "dt": "20260721"
        },
        {
          "report": "임원ㆍ주요주주특정증권등소유상황보고서",
          "url": "https://dart.fss.or.kr/dsaf001/main.do?rcpNo=20260721000300",
          "dt": "20260721"
        },
        {
          "report": "임원ㆍ주요주주특정증권등소유상황보고서",
          "url": "https://dart.fss.or.kr/dsaf001/main.do?rcpNo=20260721000299",
          "dt": "20260721"
        },
        {
          "report": "임원ㆍ주요주주특정증권등소유상황보고서",
          "url": "https://dart.fss.or.kr/dsaf001/main.do?rcpNo=20260721000298",
          "dt": "20260721"
        },
        {
          "report": "임원ㆍ주요주주특정증권등소유상황보고서",
          "url": "https://dart.fss.or.kr/dsaf001/main.do?rcpNo=20260721000294",
          "dt": "20260721"
        },
        {
          "report": "임원ㆍ주요주주특정증권등소유상황보고서",
          "url": "https://dart.fss.or.kr/dsaf001/main.do?rcpNo=20260721000293",
          "dt": "20260721"
        },
        {
          "report": "임원ㆍ주요주주특정증권등소유상황보고서",
          "url": "https://dart.fss.or.kr/dsaf001/main.do?rcpNo=20260721000291",
          "dt": "20260721"
        },
        {
          "report": "임원ㆍ주요주주특정증권등소유상황보고서",
          "url": "https://dart.fss.or.kr/dsaf001/main.do?rcpNo=20260721000290",
          "dt": "20260721"
        },
        {
          "report": "임원ㆍ주요주주특정증권등소유상황보고서",
          "url": "https://dart.fss.or.kr/dsaf001/main.do?rcpNo=20260721000289",
          "dt": "20260721"
        },
        {
          "report": "임원ㆍ주요주주특정증권등소유상황보고서",
          "url": "https://dart.fss.or.kr/dsaf001/main.do?rcpNo=20260721000287",
          "dt": "20260721"
        },
        {
          "report": "임원ㆍ주요주주특정증권등소유상황보고서",
          "url": "https://dart.fss.or.kr/dsaf001/main.do?rcpNo=20260721000285",
          "dt": "20260721"
        },
        {
          "report": "임원ㆍ주요주주특정증권등소유상황보고서",
          "url": "https://dart.fss.or.kr/dsaf001/main.do?rcpNo=20260721000283",
          "dt": "20260721"
        },
        {
          "report": "임원ㆍ주요주주특정증권등소유상황보고서",
          "url": "https://dart.fss.or.kr/dsaf001/main.do?rcpNo=20260721000282",
          "dt": "20260721"
        },
        {
          "report": "임원ㆍ주요주주특정증권등소유상황보고서",
          "url": "https://dart.fss.or.kr/dsaf001/main.do?rcpNo=20260721000281",
          "dt": "20260721"
        },
        {
          "report": "임원ㆍ주요주주특정증권등소유상황보고서",
          "url": "https://dart.fss.or.kr/dsaf001/main.do?rcpNo=20260721000280",
          "dt": "20260721"
        },
        {
          "report": "임원ㆍ주요주주특정증권등소유상황보고서",
          "url": "https://dart.fss.or.kr/dsaf001/main.do?rcpNo=20260721000279",
          "dt": "20260721"
        },
        {
          "report": "임원ㆍ주요주주특정증권등소유상황보고서",
          "url": "https://dart.fss.or.kr/dsaf001/main.do?rcpNo=20260721000277",
          "dt": "20260721"
        },
        {
          "report": "임원ㆍ주요주주특정증권등소유상황보고서",
          "url": "https://dart.fss.or.kr/dsaf001/main.do?rcpNo=20260721000275",
          "dt": "20260721"
        },
        {
          "report": "임원ㆍ주요주주특정증권등소유상황보고서",
          "url": "https://dart.fss.or.kr/dsaf001/main.do?rcpNo=20260721000272",
          "dt": "20260721"
        },
        {
          "report": "임원ㆍ주요주주특정증권등소유상황보고서",
          "url": "https://dart.fss.or.kr/dsaf001/main.do?rcpNo=20260721000270",
          "dt": "20260721"
        },
        {
          "report": "임원ㆍ주요주주특정증권등소유상황보고서",
          "url": "https://dart.fss.or.kr/dsaf001/main.do?rcpNo=20260721000269",
          "dt": "20260721"
        },
        {
          "report": "임원ㆍ주요주주특정증권등소유상황보고서",
          "url": "https://dart.fss.or.kr/dsaf001/main.do?rcpNo=20260721000267",
          "dt": "20260721"
        },
        {
          "report": "임원ㆍ주요주주특정증권등소유상황보고서",
          "url": "https://dart.fss.or.kr/dsaf001/main.do?rcpNo=20260721000266",
          "dt": "20260721"
        },
        {
          "report": "임원ㆍ주요주주특정증권등소유상황보고서",
          "url": "https://dart.fss.or.kr/dsaf001/main.do?rcpNo=20260721000265",
          "dt": "20260721"
        },
        {
          "report": "임원ㆍ주요주주특정증권등소유상황보고서",
          "url": "https://dart.fss.or.kr/dsaf001/main.do?rcpNo=20260721000264",
          "dt": "20260721"
        },
        {
          "report": "임원ㆍ주요주주특정증권등소유상황보고서",
          "url": "https://dart.fss.or.kr/dsaf001/main.do?rcpNo=20260721000263",
          "dt": "20260721"
        },
        {
          "report": "임원ㆍ주요주주특정증권등소유상황보고서",
          "url": "https://dart.fss.or.kr/dsaf001/main.do?rcpNo=20260721000262",
          "dt": "20260721"
        },
        {
          "report": "임원ㆍ주요주주특정증권등소유상황보고서",
          "url": "https://dart.fss.or.kr/dsaf001/main.do?rcpNo=20260721000259",
          "dt": "20260721"
        },
        {
          "report": "임원ㆍ주요주주특정증권등소유상황보고서",
          "url": "https://dart.fss.or.kr/dsaf001/main.do?rcpNo=20260721000258",
          "dt": "20260721"
        },
        {
          "report": "임원ㆍ주요주주특정증권등소유상황보고서",
          "url": "https://dart.fss.or.kr/dsaf001/main.do?rcpNo=20260721000256",
          "dt": "20260721"
        },
        {
          "report": "임원ㆍ주요주주특정증권등소유상황보고서",
          "url": "https://dart.fss.or.kr/dsaf001/main.do?rcpNo=20260721000254",
          "dt": "20260721"
        },
        {
          "report": "임원ㆍ주요주주특정증권등소유상황보고서",
          "url": "https://dart.fss.or.kr/dsaf001/main.do?rcpNo=20260721000252",
          "dt": "20260721"
        },
        {
          "report": "임원ㆍ주요주주특정증권등소유상황보고서",
          "url": "https://dart.fss.or.kr/dsaf001/main.do?rcpNo=20260721000251",
          "dt": "20260721"
        },
        {
          "report": "임원ㆍ주요주주특정증권등소유상황보고서",
          "url": "https://dart.fss.or.kr/dsaf001/main.do?rcpNo=20260721000250",
          "dt": "20260721"
        },
        {
          "report": "임원ㆍ주요주주특정증권등소유상황보고서",
          "url": "https://dart.fss.or.kr/dsaf001/main.do?rcpNo=20260721000249",
          "dt": "20260721"
        },
        {
          "report": "임원ㆍ주요주주특정증권등소유상황보고서",
          "url": "https://dart.fss.or.kr/dsaf001/main.do?rcpNo=20260721000246",
          "dt": "20260721"
        },
        {
          "report": "임원ㆍ주요주주특정증권등소유상황보고서",
          "url": "https://dart.fss.or.kr/dsaf001/main.do?rcpNo=20260721000245",
          "dt": "20260721"
        },
        {
          "report": "임원ㆍ주요주주특정증권등소유상황보고서",
          "url": "https://dart.fss.or.kr/dsaf001/main.do?rcpNo=20260721000244",
          "dt": "20260721"
        },
        {
          "report": "임원ㆍ주요주주특정증권등소유상황보고서",
          "url": "https://dart.fss.or.kr/dsaf001/main.do?rcpNo=20260721000241",
          "dt": "20260721"
        },
        {
          "report": "임원ㆍ주요주주특정증권등소유상황보고서",
          "url": "https://dart.fss.or.kr/dsaf001/main.do?rcpNo=20260721000239",
          "dt": "20260721"
        },
        {
          "report": "임원ㆍ주요주주특정증권등소유상황보고서",
          "url": "https://dart.fss.or.kr/dsaf001/main.do?rcpNo=20260721000238",
          "dt": "20260721"
        },
        {
          "report": "임원ㆍ주요주주특정증권등소유상황보고서",
          "url": "https://dart.fss.or.kr/dsaf001/main.do?rcpNo=20260721000235",
          "dt": "20260721"
        },
        {
          "report": "임원ㆍ주요주주특정증권등소유상황보고서",
          "url": "https://dart.fss.or.kr/dsaf001/main.do?rcpNo=20260721000234",
          "dt": "20260721"
        },
        {
          "report": "임원ㆍ주요주주특정증권등소유상황보고서",
          "url": "https://dart.fss.or.kr/dsaf001/main.do?rcpNo=20260721000233",
          "dt": "20260721"
        },
        {
          "report": "임원ㆍ주요주주특정증권등소유상황보고서",
          "url": "https://dart.fss.or.kr/dsaf001/main.do?rcpNo=20260721000232",
          "dt": "20260721"
        },
        {
          "report": "임원ㆍ주요주주특정증권등소유상황보고서",
          "url": "https://dart.fss.or.kr/dsaf001/main.do?rcpNo=20260721000230",
          "dt": "20260721"
        },
        {
          "report": "임원ㆍ주요주주특정증권등소유상황보고서",
          "url": "https://dart.fss.or.kr/dsaf001/main.do?rcpNo=20260721000228",
          "dt": "20260721"
        },
        {
          "report": "임원ㆍ주요주주특정증권등소유상황보고서",
          "url": "https://dart.fss.or.kr/dsaf001/main.do?rcpNo=20260721000227",
          "dt": "20260721"
        },
        {
          "report": "임원ㆍ주요주주특정증권등소유상황보고서",
          "url": "https://dart.fss.or.kr/dsaf001/main.do?rcpNo=20260721000226",
          "dt": "20260721"
        },
        {
          "report": "임원ㆍ주요주주특정증권등소유상황보고서",
          "url": "https://dart.fss.or.kr/dsaf001/main.do?rcpNo=20260721000225",
          "dt": "20260721"
        },
        {
          "report": "임원ㆍ주요주주특정증권등소유상황보고서",
          "url": "https://dart.fss.or.kr/dsaf001/main.do?rcpNo=20260721000224",
          "dt": "20260721"
        },
        {
          "report": "임원ㆍ주요주주특정증권등소유상황보고서",
          "url": "https://dart.fss.or.kr/dsaf001/main.do?rcpNo=20260721000223",
          "dt": "20260721"
        },
        {
          "report": "임원ㆍ주요주주특정증권등소유상황보고서",
          "url": "https://dart.fss.or.kr/dsaf001/main.do?rcpNo=20260721000222",
          "dt": "20260721"
        },
        {
          "report": "임원ㆍ주요주주특정증권등소유상황보고서",
          "url": "https://dart.fss.or.kr/dsaf001/main.do?rcpNo=20260721000221",
          "dt": "20260721"
        },
        {
          "report": "임원ㆍ주요주주특정증권등소유상황보고서",
          "url": "https://dart.fss.or.kr/dsaf001/main.do?rcpNo=20260721000216",
          "dt": "20260721"
        },
        {
          "report": "임원ㆍ주요주주특정증권등소유상황보고서",
          "url": "https://dart.fss.or.kr/dsaf001/main.do?rcpNo=20260721000214",
          "dt": "20260721"
        },
        {
          "report": "임원ㆍ주요주주특정증권등소유상황보고서",
          "url": "https://dart.fss.or.kr/dsaf001/main.do?rcpNo=20260721000213",
          "dt": "20260721"
        },
        {
          "report": "임원ㆍ주요주주특정증권등소유상황보고서",
          "url": "https://dart.fss.or.kr/dsaf001/main.do?rcpNo=20260721000211",
          "dt": "20260721"
        },
        {
          "report": "임원ㆍ주요주주특정증권등소유상황보고서",
          "url": "https://dart.fss.or.kr/dsaf001/main.do?rcpNo=20260721000210",
          "dt": "20260721"
        },
        {
          "report": "임원ㆍ주요주주특정증권등소유상황보고서",
          "url": "https://dart.fss.or.kr/dsaf001/main.do?rcpNo=20260721000209",
          "dt": "20260721"
        },
        {
          "report": "임원ㆍ주요주주특정증권등소유상황보고서",
          "url": "https://dart.fss.or.kr/dsaf001/main.do?rcpNo=20260721000207",
          "dt": "20260721"
        },
        {
          "report": "임원ㆍ주요주주특정증권등소유상황보고서",
          "url": "https://dart.fss.or.kr/dsaf001/main.do?rcpNo=20260721000206",
          "dt": "20260721"
        },
        {
          "report": "임원ㆍ주요주주특정증권등소유상황보고서",
          "url": "https://dart.fss.or.kr/dsaf001/main.do?rcpNo=20260721000205",
          "dt": "20260721"
        },
        {
          "report": "임원ㆍ주요주주특정증권등소유상황보고서",
          "url": "https://dart.fss.or.kr/dsaf001/main.do?rcpNo=20260721000204",
          "dt": "20260721"
        },
        {
          "report": "임원ㆍ주요주주특정증권등소유상황보고서",
          "url": "https://dart.fss.or.kr/dsaf001/main.do?rcpNo=20260721000201",
          "dt": "20260721"
        },
        {
          "report": "임원ㆍ주요주주특정증권등소유상황보고서",
          "url": "https://dart.fss.or.kr/dsaf001/main.do?rcpNo=20260721000200",
          "dt": "20260721"
        },
        {
          "report": "임원ㆍ주요주주특정증권등소유상황보고서",
          "url": "https://dart.fss.or.kr/dsaf001/main.do?rcpNo=20260721000199",
          "dt": "20260721"
        },
        {
          "report": "임원ㆍ주요주주특정증권등소유상황보고서",
          "url": "https://dart.fss.or.kr/dsaf001/main.do?rcpNo=20260721000198",
          "dt": "20260721"
        },
        {
          "report": "임원ㆍ주요주주특정증권등소유상황보고서",
          "url": "https://dart.fss.or.kr/dsaf001/main.do?rcpNo=20260721000197",
          "dt": "20260721"
        },
        {
          "report": "임원ㆍ주요주주특정증권등소유상황보고서",
          "url": "https://dart.fss.or.kr/dsaf001/main.do?rcpNo=20260721000195",
          "dt": "20260721"
        },
        {
          "report": "임원ㆍ주요주주특정증권등소유상황보고서",
          "url": "https://dart.fss.or.kr/dsaf001/main.do?rcpNo=20260721000194",
          "dt": "20260721"
        },
        {
          "report": "임원ㆍ주요주주특정증권등소유상황보고서",
          "url": "https://dart.fss.or.kr/dsaf001/main.do?rcpNo=20260721000193",
          "dt": "20260721"
        },
        {
          "report": "임원ㆍ주요주주특정증권등소유상황보고서",
          "url": "https://dart.fss.or.kr/dsaf001/main.do?rcpNo=20260721000191",
          "dt": "20260721"
        },
        {
          "report": "임원ㆍ주요주주특정증권등소유상황보고서",
          "url": "https://dart.fss.or.kr/dsaf001/main.do?rcpNo=20260721000189",
          "dt": "20260721"
        },
        {
          "report": "임원ㆍ주요주주특정증권등소유상황보고서",
          "url": "https://dart.fss.or.kr/dsaf001/main.do?rcpNo=20260721000188",
          "dt": "20260721"
        },
        {
          "report": "임원ㆍ주요주주특정증권등소유상황보고서",
          "url": "https://dart.fss.or.kr/dsaf001/main.do?rcpNo=20260721000186",
          "dt": "20260721"
        },
        {
          "report": "임원ㆍ주요주주특정증권등소유상황보고서",
          "url": "https://dart.fss.or.kr/dsaf001/main.do?rcpNo=20260721000181",
          "dt": "20260721"
        },
        {
          "report": "임원ㆍ주요주주특정증권등소유상황보고서",
          "url": "https://dart.fss.or.kr/dsaf001/main.do?rcpNo=20260721000180",
          "dt": "20260721"
        },
        {
          "report": "임원ㆍ주요주주특정증권등소유상황보고서",
          "url": "https://dart.fss.or.kr/dsaf001/main.do?rcpNo=20260721000179",
          "dt": "20260721"
        },
        {
          "report": "임원ㆍ주요주주특정증권등소유상황보고서",
          "url": "https://dart.fss.or.kr/dsaf001/main.do?rcpNo=20260721000175",
          "dt": "20260721"
        },
        {
          "report": "[기재정정]임원ㆍ주요주주특정증권등소유상황보고서",
          "url": "https://dart.fss.or.kr/dsaf001/main.do?rcpNo=20260721000174",
          "dt": "20260721"
        },
        {
          "report": "임원ㆍ주요주주특정증권등소유상황보고서",
          "url": "https://dart.fss.or.kr/dsaf001/main.do?rcpNo=20260721000173",
          "dt": "20260721"
        },
        {
          "report": "임원ㆍ주요주주특정증권등소유상황보고서",
          "url": "https://dart.fss.or.kr/dsaf001/main.do?rcpNo=20260721000172",
          "dt": "20260721"
        },
        {
          "report": "임원ㆍ주요주주특정증권등소유상황보고서",
          "url": "https://dart.fss.or.kr/dsaf001/main.do?rcpNo=20260721000170",
          "dt": "20260721"
        },
        {
          "report": "임원ㆍ주요주주특정증권등소유상황보고서",
          "url": "https://dart.fss.or.kr/dsaf001/main.do?rcpNo=20260721000169",
          "dt": "20260721"
        },
        {
          "report": "임원ㆍ주요주주특정증권등소유상황보고서",
          "url": "https://dart.fss.or.kr/dsaf001/main.do?rcpNo=20260721000166",
          "dt": "20260721"
        },
        {
          "report": "임원ㆍ주요주주특정증권등소유상황보고서",
          "url": "https://dart.fss.or.kr/dsaf001/main.do?rcpNo=20260721000165",
          "dt": "20260721"
        },
        {
          "report": "임원ㆍ주요주주특정증권등소유상황보고서",
          "url": "https://dart.fss.or.kr/dsaf001/main.do?rcpNo=20260721000096",
          "dt": "20260721"
        },
        {
          "report": "[기재정정]임원ㆍ주요주주특정증권등소유상황보고서",
          "url": "https://dart.fss.or.kr/dsaf001/main.do?rcpNo=20260721000075",
          "dt": "20260721"
        },
        {
          "report": "[기재정정]임원ㆍ주요주주특정증권등소유상황보고서",
          "url": "https://dart.fss.or.kr/dsaf001/main.do?rcpNo=20260721000069",
          "dt": "20260721"
        },
        {
          "report": "[기재정정]임원ㆍ주요주주특정증권등소유상황보고서",
          "url": "https://dart.fss.or.kr/dsaf001/main.do?rcpNo=20260721000062",
          "dt": "20260721"
        },
        {
          "report": "임원ㆍ주요주주특정증권등소유상황보고서",
          "url": "https://dart.fss.or.kr/dsaf001/main.do?rcpNo=20260720000360",
          "dt": "20260721"
        }
      ]
    },
    {
      "code": "051360",
      "name": "토비스",
      "items": [
        {
          "report": "[기재정정]증권발행실적보고서(합병등)",
          "url": "https://dart.fss.or.kr/dsaf001/main.do?rcpNo=20260720000048",
          "dt": "20260720"
        }
      ]
    }
  ],
  "kr_holdings": [
    {
      "code": "000660",
      "name": "SK하이닉스"
    },
    {
      "code": "005380",
      "name": "현대차"
    },
    {
      "code": "005930",
      "name": "삼성전자"
    },
    {
      "code": "006400",
      "name": "삼성SDI"
    },
    {
      "code": "009150",
      "name": "삼성전기"
    },
    {
      "code": "032830",
      "name": "삼성생명"
    },
    {
      "code": "034730",
      "name": "SK"
    },
    {
      "code": "051360",
      "name": "토비스"
    },
    {
      "code": "471990",
      "name": "KODEX AI반도체핵심장비"
    }
  ]
}